Basins/__init__.py
Basins/adriatic.py
Basins/baltic.py
Basins/basic.py
Basins/basic.pyx
Basins/climate.py
Basins/entities.py
Basins/generic.py
Basins/hydrolakes.py
Basins/mediterranean.py
Basins/worldcountries.py
Basins/worldseas.py
Basins/shapes/Adriatic_WorldSeas.npy
Basins/shapes/Aegean_WorldSeas.npy
Basins/shapes/Alboran_WorldSeas.npy
Basins/shapes/ArcticOcean_WorldSeas.npy
Basins/shapes/BaffinBay_WorldSeas.npy
Basins/shapes/Balearic_WorldSeas.npy
Basins/shapes/BalticSea_WorldSeas.npy
Basins/shapes/BarentszSea_WorldSeas.npy
Basins/shapes/BeaufortSea_WorldSeas.npy
Basins/shapes/BiscayBay_WorldSeas.npy
Basins/shapes/BlackSea_WorldSeas.npy
Basins/shapes/CaribbeanSea_WorldSeas.npy
Basins/shapes/CelticSea_WorldSeas.npy
Basins/shapes/EastMed_WorldSeas.npy
Basins/shapes/GreenlandSea_WorldSeas.npy
Basins/shapes/HudsonBay_WorldSeas.npy
Basins/shapes/IndianOcean_WorldSeas.npy
Basins/shapes/Ionian_WorldSeas.npy
Basins/shapes/Kotor_WorldSeas.npy
Basins/shapes/LabradorSea_WorldSeas.npy
Basins/shapes/Ligurian_WorldSeas.npy
Basins/shapes/Mid_Adriatic.npy
Basins/shapes/Montenegro_WorldCountries.npy
Basins/shapes/NorthAtlantic_WorldSeas.npy
Basins/shapes/NorthSea_WorldSeas.npy
Basins/shapes/North_Adriatic.npy
Basins/shapes/NorwegianSea_WorldSeas.npy
Basins/shapes/PhilippineSea_WorldSeas.npy
Basins/shapes/RedSea_WorldSeas.npy
Basins/shapes/Skadar_HydroLAKES.npy
Basins/shapes/SouthAtlantic_WorldSeas.npy
Basins/shapes/SouthPacific1_WorldSeas.npy
Basins/shapes/SouthPacific2_WorldSeas.npy
Basins/shapes/South_Adriatic.npy
Basins/shapes/SouthernOcean_WorldSeas.npy
Basins/shapes/Spain_WorldCountries.npy
Basins/shapes/Tyrrhenian_WorldSeas.npy
Basins/shapes/WestMed_WorldSeas.npy
Basins/src/geometry.cpp
Basins/src/geometry.h
Basins/src/matrixMN.h
Basins-1.6.0.dist-info/LICENSE
Basins-1.6.0.dist-info/METADATA
Basins-1.6.0.dist-info/WHEEL
Basins-1.6.0.dist-info/top_level.txt
Basins-1.6.0.dist-info/RECORD
