Metadata-Version: 2.1
Name: Basins
Version: 1.6.0
Summary: Tools to specify the region of interest when analysing float, satellite or model data
Home-page: https://github.com/ElenaTerzic/Basins.git
Author: Arnau Miro, Elena Terzić
Author-email: Arnau Miro <arnau.miro@upc.edu>, Elena Terzić <elena.terzic@proton.me>
Maintainer: Arnau Miro
Maintainer-email: Arnau Miro <arnau.miro@upc.edu>
License: GNU GENERAL PUBLIC LICENSE
Project-URL: Homepage, https://github.com/ElenaTerzic/Basins
Project-URL: Bug Reports, https://github.com/ElenaTerzic/Basins/issues
Project-URL: Source, https://github.com/ElenaTerzic/Basins
Keywords: maps,plots,polygon,data,data selection
Classifier: Development Status :: 5 - Production/Stable
Classifier: Intended Audience :: Science/Research
Classifier: Topic :: Scientific/Engineering
Classifier: License :: OSI Approved :: GNU General Public License v3 (GPLv3)
Classifier: Programming Language :: Python :: 3
Classifier: Programming Language :: Python :: 3.7
Classifier: Programming Language :: Python :: 3.8
Classifier: Programming Language :: Python :: 3.9
Classifier: Programming Language :: Python :: 3.10
Classifier: Programming Language :: Python :: 3.11
Classifier: Programming Language :: Python :: 3 :: Only
Requires-Python: >=3.7
License-File: LICENSE
Requires-Dist: numpy
Requires-Dist: cython
Provides-Extra: full
